wss/__init__.py
wss/wss.py
wss_python-1.2.0.dist-info/METADATA
wss_python-1.2.0.dist-info/WHEEL
wss_python-1.2.0.dist-info/entry_points.txt
wss_python-1.2.0.dist-info/top_level.txt
wss_python-1.2.0.dist-info/RECORD
