Metadata-Version: 2.1
Name: wss-python
Version: 1.2.0
Summary: 文叔叔
Author: sanfeng
Author-email: 2669291603@qq.com
Requires-Dist: requests
Requires-Dist: base58
Requires-Dist: pycryptodomex
Requires-Dist: docopt
